LICENSE
MANIFEST.in
README.rst
VERSION
requirements.txt
setup.py
src/kser_crypto/__init__.py
src/kser_crypto/controller.py
src/kser_crypto/schemas.py
src/kser_crypto.egg-info/PKG-INFO
src/kser_crypto.egg-info/SOURCES.txt
src/kser_crypto.egg-info/dependency_links.txt
src/kser_crypto.egg-info/requires.txt
src/kser_crypto.egg-info/top_level.txt
src/kser_crypto.egg-info/zip-safe
src/kser_crypto/python_kafka/__init__.py
src/kser_crypto/python_kafka/consumer.py
src/kser_crypto/python_kafka/producer.py