Metadata-Version: 2.1
Name: kser-crypto
Version: 0.1.12
Summary: Crypto Kafka serialize python library
Home-page: https://github.com/cdumay/kser-crypto
Author: Cedric DUMAY
Author-email: cedric.dumay@gmail.com
License: MIT
Classifier: Programming Language :: Python
License-File: LICENSE
Requires-Dist: cdumay-error>=0.1.14
Requires-Dist: cdumay-result>=0.1.12
Requires-Dist: kser>=0.8.22
Requires-Dist: pysodium>=0.7.5
Provides-Extra: pykafka
Requires-Dist: kafka-python; extra == "pykafka"
Provides-Extra: tests
Requires-Dist: flake8; extra == "tests"
Requires-Dist: flake8-html; extra == "tests"
Requires-Dist: pytest; extra == "tests"
Requires-Dist: pytest-cov; extra == "tests"
Requires-Dist: pytest-html; extra == "tests"
